{
  "project_info": {
    "project_number": "867474863429",
    "project_id": "veralusso-304008",
    "storage_bucket": "veralusso-304008.appspot.com"
  },
  "client": [
    {
      "client_info": {
        "mobilesdk_app_id": "1:867474863429:android:4002ee9bb7a7215a463a2c",
        "android_client_info": {
          "package_name": "com.app.veralusso"
        }
      },
      "oauth_client": [
        {
          "client_id": "867474863429-bcenm0o26794ec73h1fv1fso2mpbshbe.apps.googleusercontent.com",
          "client_type": 1,
          "android_info": {
            "package_name": "com.app.veralusso",
            "certificate_hash": "45ec1ac495777fe2b7bc8c4e76214a1a0cd475c4"
          }
        },
        {
          "client_id": "867474863429-o2f5epepanfs6f6b1md6quha5ob3c4je.apps.googleusercontent.com",
          "client_type": 1,
          "android_info": {
            "package_name": "com.app.veralusso",
            "certificate_hash": "e50299b669c737b3c6258f37dc810405c76d9f98"
          }
        },
        {
          "client_id": "867474863429-t9adr76scare4o4phcga833t1i6f0j5l.apps.googleusercontent.com",
          "client_type": 3
        }
      ],
      "api_key": [
        {
          "current_key": "AIzaSyCHBw3sN1kgirCJ8l58YItZX7tKsdIBSV4"
        }
      ],
      "services": {
        "appinvite_service": {
          "other_platform_oauth_client": [
            {
              "client_id": "867474863429-02k3vkt8kcn4f6mmk0sd3oedj7dbjmk0.apps.googleusercontent.com",
              "client_type": 3
            },
            {
              "client_id": "867474863429-lmeclpk4sh6b5l86kp0fbg886ibfev71.apps.googleusercontent.com",
              "client_type": 2,
              "ios_info": {
                "bundle_id": "com.app.veralusso"
              }
            }
          ]
        }
      }
    }
  ],
  "configuration_version": "1"
}